ghops/__init__.py
ghops/__main__.py
ghops/cli.py
ghops/cli_utils.py
ghops/component_hooks.py
ghops/config.py
ghops/core.py
ghops/exit_codes.py
ghops/export_components.py
ghops/export_components_impl.py
ghops/format_utils.py
ghops/ghops.py
ghops/gitignore.py
ghops/hugo_export.py
ghops/metadata.py
ghops/progress.py
ghops/pypi.py
ghops/query.py
ghops/render.py
ghops/repo_filter.py
ghops/reporting.py
ghops/service.py
ghops/social.py
ghops/status.py
ghops/tags.py
ghops/utils.py
ghops/commands/__init__.py
ghops/commands/audit.py
ghops/commands/catalog.py
ghops/commands/config.py
ghops/commands/customize.py
ghops/commands/docs.py
ghops/commands/export.py
ghops/commands/get.py
ghops/commands/license.py
ghops/commands/list.py
ghops/commands/metadata.py
ghops/commands/query.py
ghops/commands/service.py
ghops/commands/social.py
ghops/commands/status.py
ghops/commands/update.py
ghops-0.7.0.dist-info/METADATA
ghops-0.7.0.dist-info/WHEEL
ghops-0.7.0.dist-info/entry_points.txt
ghops-0.7.0.dist-info/RECORD
