Metadata-Version: 2.4
Name: ghops
Version: 0.7.0
Summary: A CLI tool for managing GitHub repos
Project-URL: Homepage, https://github.com/queelius/ghops
Project-URL: Source, https://github.com/queelius/ghops
Project-URL: Issues, https://github.com/queelius/ghops/issues
Author-email: Alex Towell <lex@metafunctor.com>
License: MIT
Keywords: automation,cli,devops,git,github
Classifier: Development Status :: 4 - Beta
Classifier: Operating System :: OS Independent
Classifier: Programming Language :: Python :: 3
Classifier: Topic :: Software Development :: Version Control :: Git
Requires-Python: >=3.7
Requires-Dist: click>=8.0.0
Requires-Dist: packaging>=21.0
Requires-Dist: pathlib
Requires-Dist: pyyaml>=5.0.0
Requires-Dist: rapidfuzz
Requires-Dist: requests>=2.25.0
Requires-Dist: rich>=13.0.0
Requires-Dist: toml
Requires-Dist: tweepy
Provides-Extra: dev
Requires-Dist: black>=21.0; extra == 'dev'
Requires-Dist: coverage>=5.0; extra == 'dev'
Requires-Dist: flake8>=3.9; extra == 'dev'
Requires-Dist: mypy>=0.812; extra == 'dev'
Requires-Dist: pytest-cov>=2.0; extra == 'dev'
Requires-Dist: pytest>=6.0; extra == 'dev'
Provides-Extra: docs
Requires-Dist: ghp-import>=2.1.0; extra == 'docs'
Requires-Dist: mkdocs-material>=9.0.0; extra == 'docs'
Requires-Dist: mkdocs>=1.4.0; extra == 'docs'
Provides-Extra: export
Requires-Dist: weasyprint>=54.0; extra == 'export'
Provides-Extra: test
Requires-Dist: coverage>=5.0; extra == 'test'
Requires-Dist: pytest-cov>=2.0; extra == 'test'
Requires-Dist: pytest>=6.0; extra == 'test'
